AUTHORS.rst
LICENSE.rst
MANIFEST.in
README.rst
setup.py
django_shop_postfinance.egg-info/PKG-INFO
django_shop_postfinance.egg-info/SOURCES.txt
django_shop_postfinance.egg-info/dependency_links.txt
django_shop_postfinance.egg-info/not-zip-safe
django_shop_postfinance.egg-info/requires.txt
django_shop_postfinance.egg-info/top_level.txt
shop_postfinance/__init__.py
shop_postfinance/admin.py
shop_postfinance/forms.py
shop_postfinance/models.py
shop_postfinance/offsite_postfinance.py
shop_postfinance/utils.py
shop_postfinance/migrations/0001_initial.py
shop_postfinance/migrations/__init__.py
shop_postfinance/templates/payment.html