Metadata-Version: 1.0
Name: django-shop-postfinance
Version: 0.0.3
Summary: An postfinance payment backend
Home-page: http://www.django-shop.org/
Author: Christopher Glass
Author-email: tribaal@gmail.com
License: BSD License
Platform: OS Independent
